mw_dry_invoke/__init__.py
mw_dry_invoke/git.py
mw_dry_invoke-0.2.7.dist-info/LICENSE
mw_dry_invoke-0.2.7.dist-info/WHEEL
mw_dry_invoke-0.2.7.dist-info/METADATA
mw_dry_invoke-0.2.7.dist-info/RECORD
