Metadata-Version: 2.1
Name: mw-dry-invoke
Version: 0.2.7
Summary: Common Invoke tasks.
Home-page: https://github.com/midwatch/mw_dry_invoke
License: MIT
Author: Justin Stout
Author-email: midwatch@jstout.us
Requires-Python: >=3.8,<4.0
Classifier: Development Status :: 2 - Pre-Alpha
Classifier: Intended Audience :: Developers
Classifier: License :: OSI Approved :: MIT License
Classifier: Natural Language :: English
Classifier: Programming Language :: Python :: 3
Classifier: Programming Language :: Python :: 3.10
Classifier: Programming Language :: Python :: 3.8
Classifier: Programming Language :: Python :: 3.9
